asteroid_spinprops/__init__.py
asteroid_spinprops/ssolib/__init__.py
asteroid_spinprops/ssolib/dataprep.py
asteroid_spinprops/ssolib/modelfit.py
asteroid_spinprops/ssolib/periodest.py
asteroid_spinprops/ssolib/pipetools.py
asteroid_spinprops/ssolib/ssptools.py
asteroid_spinprops/ssolib/testing/atlas_x_ztf_testing/test_pqfile_1.parquet
asteroid_spinprops/ssolib/testing/atlas_x_ztf_testing/test_pqfile_2.parquet
asteroid_spinprops/ssolib/testing/ephemeris_testing/2000 WL152
asteroid_spinprops/ssolib/testing/ephemeris_testing/2001 PC
asteroid_spinprops/ssolib/testing/ephemeris_testing/2001 SG276
asteroid_spinprops/ssolib/testing/ephemeris_testing/2008 GX32
asteroid_spinprops/ssolib/testing/ephemeris_testing/2009 BE185
asteroid_spinprops/ssolib/testing/ephemeris_testing/2011 EY17
asteroid_spinprops/ssolib/testing/ephemeris_testing/2134 T-1
asteroid_spinprops/ssolib/testing/ephemeris_testing/Bellmore
asteroid_spinprops/ssolib/testing/ephemeris_testing/Dermott
asteroid_spinprops/ssolib/testing/ephemeris_testing/Duke
asteroid_spinprops/ssolib/testing/ephemeris_testing/Izenberg
asteroid_spinprops/ssolib/testing/ephemeris_testing/Lermontov
asteroid_spinprops/ssolib/testing/ephemeris_testing/Poullain
asteroid_spinprops/ssolib/testing/ephemeris_testing/Sonneberga
asteroid_spinprops/ssolib/testing/testing_ssoname_keys.pkl
asteroid_spinprops/ssolib/utils.py
asteroid_spinprops-1.3.9.dist-info/METADATA
asteroid_spinprops-1.3.9.dist-info/WHEEL
asteroid_spinprops-1.3.9.dist-info/RECORD
