Metadata-Version: 2.4
Name: asteroid_spinprops
Version: 1.3.9
Summary: Collection of tools used for fitting sHG1G2 and SOCCA photometric models to sparse asteroid photometry
License: MIT
Author: Odysseas
Author-email: odysseas.xenos@proton.me
Requires-Python: >=3.9
Classifier: License :: OSI Approved :: MIT License
Classifier: Programming Language :: Python :: 3
Classifier: Programming Language :: Python :: 3.9
Classifier: Programming Language :: Python :: 3.10
Classifier: Programming Language :: Python :: 3.11
Classifier: Programming Language :: Python :: 3.12
Classifier: Programming Language :: Python :: 3.13
Classifier: Programming Language :: Python :: 3.14
Requires-Dist: astropy (>=6.0)
Requires-Dist: fink-utils (>=0.48.0)
Requires-Dist: nifty-ls (>=1.1.0)
Requires-Dist: pandas (>=2.3)
Requires-Dist: pyarrow (>=18.1)
Requires-Dist: sbpy (>=0.5.0)
Requires-Dist: scipy (>=1.10)
Requires-Dist: tqdm (>=4.67)
Project-URL: Homepage, https://gitlab.com/odysseas_xenos/asteroid-spinprops
Project-URL: Repository, https://gitlab.com/odysseas_xenos/asteroid-spinprops
